odoo/addons/fieldservice_partner_multi_relation/README.rst
odoo/addons/fieldservice_partner_multi_relation/__init__.py
odoo/addons/fieldservice_partner_multi_relation/__manifest__.py
odoo/addons/fieldservice_partner_multi_relation/data/demo.xml
odoo/addons/fieldservice_partner_multi_relation/models/__init__.py
odoo/addons/fieldservice_partner_multi_relation/models/res_partner.py
odoo/addons/fieldservice_partner_multi_relation/models/res_partner_relation_type.py
odoo/addons/fieldservice_partner_multi_relation/readme/CONFIGURE.rst
odoo/addons/fieldservice_partner_multi_relation/readme/CONTRIBUTORS.rst
odoo/addons/fieldservice_partner_multi_relation/readme/CREDITS.rst
odoo/addons/fieldservice_partner_multi_relation/readme/DESCRIPTION.rst
odoo/addons/fieldservice_partner_multi_relation/readme/INSTALL.rst
odoo/addons/fieldservice_partner_multi_relation/readme/ROADMAP.rst
odoo/addons/fieldservice_partner_multi_relation/readme/USAGE.rst
odoo/addons/fieldservice_partner_multi_relation/static/description/icon.png
odoo/addons/fieldservice_partner_multi_relation/static/description/index.html
odoo11_addon_fieldservice_partner_multi_relation-11.0.1.0.0.99.dev6.dist-info/METADATA
odoo11_addon_fieldservice_partner_multi_relation-11.0.1.0.0.99.dev6.dist-info/WHEEL
odoo11_addon_fieldservice_partner_multi_relation-11.0.1.0.0.99.dev6.dist-info/top_level.txt
odoo11_addon_fieldservice_partner_multi_relation-11.0.1.0.0.99.dev6.dist-info/RECORD
